dbay/__init__.py
dbay/client.py
dbay/direct.py
dbay/http.py
dbay/state.py
dbay/addons/__init__.py
dbay/addons/vsense.py
dbay/addons/vsource.py
dbay/modules/__init__.py
dbay/modules/adc4d.py
dbay/modules/dac16d.py
dbay/modules/dac4d.py
dbay/modules/dac4eth.py
dbay/modules/empty.py
dbay/modules/fafd.py
dbay/modules/hic4.py
dbay-0.2.0.dist-info/METADATA
dbay-0.2.0.dist-info/WHEEL
dbay-0.2.0.dist-info/top_level.txt
dbay-0.2.0.dist-info/RECORD
