Metadata-Version: 2.1
Name: dbay
Version: 0.2.0
Summary: Unified dual-mode client (HTTP GUI + direct UDP/Serial) for Device Bay VME racks
Author-email: Andrew Mueller <andrewstermueller@gmail.com>
License: MIT
Project-URL: Homepage, https://github.com/bkorzh/dbay
Project-URL: Documentation, https://bkorzh.github.io/dbay/
Keywords: dbay,client,api
Classifier: Development Status :: 3 - Alpha
Classifier: Intended Audience :: Developers
Classifier: License :: OSI Approved :: MIT License
Classifier: Programming Language :: Python :: 3
Classifier: Programming Language :: Python :: 3.8
Classifier: Programming Language :: Python :: 3.9
Classifier: Programming Language :: Python :: 3.10
Classifier: Programming Language :: Python :: 3.11
Classifier: Programming Language :: Python :: 3.12
Requires-Python: >=3.8
Requires-Dist: pydantic>=2.10.6
Requires-Dist: pyserial>=3.5
Requires-Dist: requests>=2.32.3
